README.rst
setup.py
coltab/__init__.py
coltab/coltab.py
coltab.egg-info/PKG-INFO
coltab.egg-info/SOURCES.txt
coltab.egg-info/dependency_links.txt
coltab.egg-info/requires.txt
coltab.egg-info/top_level.txt
coltab.egg-info/zip-safe