Metadata-Version: 1.1
Name: coltab
Version: 1.0.1
Summary: colorful tables for the terminal
Home-page: https://github.com/richardbann/coltab
Author: Richard Bann
Author-email: richardbann@gmail.com
License: MIT license
Platform: UNKNOWN
Classifier: Intended Audience :: Developers
Classifier: License :: OSI Approved :: MIT License
Classifier: Natural Language :: English
Classifier: Programming Language :: Python :: 3
